docs/__init__.py
docs/conf.py
pypi_template/__init__.py
pypi_template/__main__.py
pypi_template/module.py
pypi_template/pip.py
pypi_template/util.py
pypi_template/templates/(dot)env
pypi_template/templates/(dot)gitignore
pypi_template/templates/.gitignore
pypi_template/templates/.readthedocs.yaml
pypi_template/templates/LICENSE.txt
pypi_template/templates/MANIFEST.in
pypi_template/templates/Makefile
pypi_template/templates/__init__.py
pypi_template/templates/requirements.docs.txt
pypi_template/templates/requirements.test.txt
pypi_template/templates/requirements.txt
pypi_template/templates/setup.py
pypi_template/templates/tox.ini
pypi_template/templates/(dot)github/README.md
pypi_template/templates/(dot)github/__init__.py
pypi_template/templates/(dot)github/workflows/__init__.py
pypi_template/templates/(dot)github/workflows/test.yaml
pypi_template/templates/(package_module_name)/__init__.py
pypi_template/templates/(package_module_name)/__main__.py
pypi_template/templates/(package_module_name)/module.py
pypi_template/templates/base/__init__.py
pypi_template/templates/base/classifiers.txt
pypi_template/templates/base/index.md
pypi_template/templates/docs/Makefile
pypi_template/templates/docs/__init__.py
pypi_template/templates/docs/code.md
pypi_template/templates/docs/conf.py
pypi_template/templates/docs/contributing.md
pypi_template/templates/docs/getting-started.md
pypi_template/templates/docs/index.md
pypi_template/templates/docs/make.bat
pypi_template/templates/docs/whats-in-the-box.md
pypi_template/templates/docs/_static/.gitignore
pypi_template/templates/docs/_static/__init__.py
pypi_template/templates/tests/__init__.py
pypi_template/templates/tests/test_example.py
pypi_template-1.5.1.dist-info/licenses/LICENSE.txt
tests/__init__.py
tests/test_example.py
tests/test_values.py
pypi_template-1.5.1.dist-info/METADATA
pypi_template-1.5.1.dist-info/WHEEL
pypi_template-1.5.1.dist-info/entry_points.txt
pypi_template-1.5.1.dist-info/top_level.txt
pypi_template-1.5.1.dist-info/RECORD
