Metadata-Version: 2.4
Name: pypi-template
Version: 1.5.1
Summary: Template-based common/best practices for managing a Python package on PyPi
Home-page: https://github.com/christophevg/pypi-template
Author: Christophe VG
License: MIT
Keywords: python pypi package management template
Classifier: Environment :: Console
Classifier: Development Status :: 5 - Production/Stable
Classifier: Intended Audience :: Developers
Classifier: Intended Audience :: System Administrators
Classifier: Topic :: Software Development
Classifier: Programming Language :: Python
Classifier: Programming Language :: Python :: 3.9
Classifier: Programming Language :: Python :: 3.10
Classifier: Programming Language :: Python :: 3.11
Classifier: Programming Language :: Python :: 3.12
License-File: LICENSE.txt
Requires-Dist: jinja2
Requires-Dist: pyyaml
Requires-Dist: prompt-toolkit
Requires-Dist: colorama
Requires-Dist: fire
Requires-Dist: importlib-resources
Requires-Dist: requests
Requires-Dist: packaging
Dynamic: author
Dynamic: classifier
Dynamic: description
Dynamic: description-content-type
Dynamic: home-page
Dynamic: keywords
Dynamic: license
Dynamic: license-file
Dynamic: requires-dist
Dynamic: summary
